README.rst
setup.py
Fantasy_Basketball/Dataframe_Augmenter.py
Fantasy_Basketball/Download.py
Fantasy_Basketball/ESPN_League.py
Fantasy_Basketball/Fantasy_Basketball.py
Fantasy_Basketball/HTML_To_Pandas.py
Fantasy_Basketball/Plot.py
Fantasy_Basketball/Process.py
Fantasy_Basketball/Raw_Stats.py
Fantasy_Basketball/Stats.py
Fantasy_Basketball/Util.py
Fantasy_Basketball/Web.py
Fantasy_Basketball/__init__.py
Fantasy_Basketball/reformatTeamData.py
Fantasy_Basketball.egg-info/PKG-INFO
Fantasy_Basketball.egg-info/SOURCES.txt
Fantasy_Basketball.egg-info/dependency_links.txt
Fantasy_Basketball.egg-info/requires.txt
Fantasy_Basketball.egg-info/top_level.txt
scripts/FB_Manager.py