Metadata-Version: 1.0
Name: Fantasy-Basketball
Version: 0.2
Summary: A package that fetches, processes and visualizes fantasy basketball statistics
Home-page: https://github.com/dwwkelly/fantasy_basketball
Author: Devin Kelly
Author-email: dwwkelly@fastmail.fm
License: GPL3
Keywords: fantasy basketball pandas
Platform: UNKNOWN
